[
    {
        "id": "c50837804c264",
        "next_nodes": [
            "5d5dc4b3b9f34"
        ],
        "prev_nodes": [],
        "next_node_distances_m": {},
        "x_meters": 0.0,
        "y_meters": 0.0,
        "type": "Transformer"
    },
    {
        "id": "5d5dc4b3b9f34",
        "next_nodes": [
            "e4c19b31de714"
        ],
        "prev_nodes": [
            "c50837804c264"
        ],
        "next_node_distances_m": {},
        "x_meters": 2.039175009165146,
        "y_meters": 2.5372015402851256,
        "type": "house",
        "HouseID": 653,
        "voltage_data": [],
        "predicted_phase": "B",
        "solar": false
    },
    {
        "id": "e4c19b31de714",
        "next_nodes": [
            "1b3e0a2b51f54"
        ],
        "prev_nodes": [
            "5d5dc4b3b9f34"
        ],
        "next_node_distances_m": {},
        "x_meters": -0.8519141299185957,
        "y_meters": -4.37679427035122,
        "type": "house",
        "HouseID": 654,
        "voltage_data": [],
        "predicted_phase": "B",
        "solar": true
    },
    {
        "id": "1b3e0a2b51f54",
        "next_nodes": [
            "d8643f15409c4"
        ],
        "prev_nodes": [
            "e4c19b31de714"
        ],
        "next_node_distances_m": {},
        "x_meters": -4.893308062303397,
        "y_meters": -0.7832180901711343,
        "type": "house",
        "HouseID": 655,
        "voltage_data": [],
        "predicted_phase": "B",
        "solar": false
    },
    {
        "id": "d8643f15409c4",
        "next_nodes": [
            "cbf2b6dc1d004"
        ],
        "prev_nodes": [
            "1b3e0a2b51f54"
        ],
        "next_node_distances_m": {},
        "x_meters": 2.036484684418345,
        "y_meters": 4.899127544051803,
        "type": "house",
        "HouseID": 656,
        "voltage_data": [],
        "predicted_phase": "B",
        "solar": false
    },
    {
        "id": "cbf2b6dc1d004",
        "next_nodes": [
            "bb76e15b5d454"
        ],
        "prev_nodes": [
            "d8643f15409c4"
        ],
        "next_node_distances_m": {},
        "x_meters": 3.0655687849100435,
        "y_meters": -4.769449089414391,
        "type": "house",
        "HouseID": 657,
        "voltage_data": [],
        "predicted_phase": "A",
        "solar": false
    },
    {
        "id": "bb76e15b5d454",
        "next_nodes": [
            "87daf80f31614"
        ],
        "prev_nodes": [
            "cbf2b6dc1d004"
        ],
        "next_node_distances_m": {},
        "x_meters": 3.5744991363058105,
        "y_meters": -4.266464740482699,
        "type": "house",
        "HouseID": 658,
        "voltage_data": [],
        "predicted_phase": "C",
        "solar": true
    },
    {
        "id": "87daf80f31614",
        "next_nodes": [
            "f28d78562a6c4"
        ],
        "prev_nodes": [
            "bb76e15b5d454"
        ],
        "next_node_distances_m": {},
        "x_meters": 4.680023994337526,
        "y_meters": -3.83761566054182,
        "type": "house",
        "HouseID": 659,
        "voltage_data": [],
        "predicted_phase": "A",
        "solar": true
    },
    {
        "id": "f28d78562a6c4",
        "next_nodes": [],
        "prev_nodes": [
            "87daf80f31614"
        ],
        "next_node_distances_m": {},
        "x_meters": -2.158315033892989,
        "y_meters": 3.377062291623277,
        "type": "house",
        "HouseID": 660,
        "voltage_data": [],
        "predicted_phase": "A",
        "solar": true
    }
]